lesley/__init__.py
lesley/lesley.py
lesley-0.3.0.dist-info/METADATA
lesley-0.3.0.dist-info/WHEEL
lesley-0.3.0.dist-info/top_level.txt
lesley-0.3.0.dist-info/RECORD
