Metadata-Version: 2.2
Name: lesley
Version: 0.3.0
Summary: Lesley is a lightweight Python package designed to create interactive, github-style, calendar-based heatmaps using altair.
Author-email: M Iqbal Tawakal <mit.iqi@gmail.com>
Project-URL: Repository, https://github.com/mitbal/lesley.git
Keywords: heatmap,visualisation,calendar,daily,matplotlib,github plot,month plot,date plot,plot,plotting
Classifier: License :: OSI Approved :: MIT License
Classifier: Programming Language :: Python :: 3
Classifier: Operating System :: OS Independent
Requires-Python: >=3.11
Requires-Dist: numpy>=1.26.4
Requires-Dist: seaborn>=0.13.2
Requires-Dist: matplotlib>=3.9.0
Requires-Dist: altair>=4.2.2
